cloudflare_cli/Cloudflare.py
cloudflare_cli/__init__.py
cloudflare_cli-0.3.dist-info/DESCRIPTION.rst
cloudflare_cli-0.3.dist-info/METADATA
cloudflare_cli-0.3.dist-info/RECORD
cloudflare_cli-0.3.dist-info/WHEEL
cloudflare_cli-0.3.dist-info/entry_points.txt
cloudflare_cli-0.3.dist-info/metadata.json
cloudflare_cli-0.3.dist-info/top_level.txt
