Metadata-Version: 2.0
Name: cloudflare-cli
Version: 0.3
Summary: A command line tool for managing vCenter and ESXi servers
Home-page: http://github.com/Moshe-Immerman/cloudflare-cli
Author: Moshe Immerman
Author-email: name.surname@gmail.com
License: BSD
Platform: any
Requires-Dist: cloudflare
Requires-Dist: sh
